LICENSE
README.md
pyproject.toml
setup.py
Cattery/__init__.py
Cattery/qt.py
Cattery/Calico/Flagger.py
Cattery/Calico/FunkOps.py
Cattery/Calico/ParmTables.py
Cattery/Calico/__init__.py
Cattery/Calico/calico-flagger.py
Cattery/Calico/calico-generic.py
Cattery/Calico/calico-oldflagger.py
Cattery/Calico/calico-parmgroomer.py
Cattery/Calico/calico-stefcal.py
Cattery/Calico/calico-view-ms.py
Cattery/Calico/calico-wsrt-old.py
Cattery/Calico/calico-wsrt-tens.py
Cattery/Calico/calico_model_iono_RM.py
Cattery/Calico/OMS/__init__.py
Cattery/Calico/OMS/central_point_source.py
Cattery/Calico/OMS/gradient_mim.py
Cattery/Calico/OMS/ifr_based_errors.py
Cattery/Calico/OMS/model_3C343.py
Cattery/Calico/OMS/polarization_jones.py
Cattery/Calico/OMS/solvable_jones.py
Cattery/Calico/OMS/solvable_pointing_errors.py
Cattery/Calico/OMS/solvable_position_shifts.py
Cattery/Calico/OMS/solvable_refraction.py
Cattery/Calico/OMS/solvable_sky_jones.py
Cattery/Calico/OMS/wsrt_beams.py
Cattery/Calico/OMS/wsrt_cos3_beam.py
Cattery/Calico/OMS/StefCal/DataTiler.py
Cattery/Calico/OMS/StefCal/Gain2x2.py
Cattery/Calico/OMS/StefCal/Gain2x2a.py
Cattery/Calico/OMS/StefCal/GainDiag.py
Cattery/Calico/OMS/StefCal/GainDiagCommon.py
Cattery/Calico/OMS/StefCal/GainDiagPhase.py
Cattery/Calico/OMS/StefCal/GainOpts.py
Cattery/Calico/OMS/StefCal/MatrixOps.py
Cattery/Calico/OMS/StefCal/StefCal.py
Cattery/Calico/OMS/StefCal/__init__.py
Cattery/Calico/OMS/StefCal/Pyxides/__init__.py
Cattery/Calico/OMS/StefCal/Pyxides/stefcal.py
Cattery/LSM/LSM.py
Cattery/LSM/LSM_Sixpack.py
Cattery/LSM/LSM_inner.py
Cattery/LSM/__init__.py
Cattery/LSM/common_utils.py
Cattery/LSM/transform.py
Cattery/LSM/test/3C343.txt
Cattery/LSM/test/3C343_all.txt
Cattery/LSM/test/3C343_nvss.txt
Cattery/LSM/test/3C343_nvssc.txt
Cattery/LSM/test/3C343_wenss.txt
Cattery/LSM/test/MG_LSM_test.py
Cattery/Lions/MIM_model.py
Cattery/Lions/PrintPyNode.py
Cattery/Lions/SimCa.py
Cattery/Lions/ZJones.py
Cattery/Lions/__init__.py
Cattery/Lions/gridded_sky.py
meqtrees_cattery.egg-info/PKG-INFO
meqtrees_cattery.egg-info/SOURCES.txt
meqtrees_cattery.egg-info/dependency_links.txt
meqtrees_cattery.egg-info/requires.txt
meqtrees_cattery.egg-info/top_level.txt