Metadata-Version: 2.4
Name: meqtrees_cattery
Version: 1.8.0rc2
Summary: MeqTrees-based frameworks for simulation and calibration of radio interferometers 
Home-page: https://github.com/ska-sa/meqtrees-cattery
Author: Oleg Smirnov
Author-email: osmirnov@gmail.com
Requires-Python: >=3.0.0
License-File: LICENSE
Requires-Dist: numpy>=1.16
Requires-Dist: purr
Requires-Dist: astropy>=3.0.0
Requires-Dist: python_casacore
Requires-Dist: scipy
Requires-Dist: astro_kittens
Requires-Dist: astro_pyxis
Requires-Dist: six
Dynamic: author
Dynamic: author-email
Dynamic: home-page
Dynamic: license-file
Dynamic: requires-dist
Dynamic: requires-python
Dynamic: summary
